skill_update/LICENSE.md
skill_update/README.md
skill_update/__init__.py
skill_update/skill.json
skill_update/version.py
skill_update/locale/en-us/dialog/alpha.dialog
skill_update/locale/en-us/dialog/ask_change_update_track.dialog
skill_update/locale/en-us/dialog/ask_download_image.dialog
skill_update/locale/en-us/dialog/ask_overwrite_drive.dialog
skill_update/locale/en-us/dialog/ask_update_anyways.dialog
skill_update/locale/en-us/dialog/ask_update_configuration.dialog
skill_update/locale/en-us/dialog/beta.dialog
skill_update/locale/en-us/dialog/check_error.dialog
skill_update/locale/en-us/dialog/check_updates.dialog
skill_update/locale/en-us/dialog/confirm_change_update_track.dialog
skill_update/locale/en-us/dialog/confirm_no_change_update_track.dialog
skill_update/locale/en-us/dialog/core_version.dialog
skill_update/locale/en-us/dialog/downloading_image.dialog
skill_update/locale/en-us/dialog/drive_instructions.dialog
skill_update/locale/en-us/dialog/error_installing_os.dialog
skill_update/locale/en-us/dialog/error_offline.dialog
skill_update/locale/en-us/dialog/error_unknown.dialog
skill_update/locale/en-us/dialog/error_updating_os.dialog
skill_update/locale/en-us/dialog/help_online.dialog
skill_update/locale/en-us/dialog/help_support.dialog
skill_update/locale/en-us/dialog/installation_complete.dialog
skill_update/locale/en-us/dialog/no_image_file.dialog
skill_update/locale/en-us/dialog/no_valid_device.dialog
skill_update/locale/en-us/dialog/not_updating.dialog
skill_update/locale/en-us/dialog/notify_download_complete.dialog
skill_update/locale/en-us/dialog/notify_download_failed.dialog
skill_update/locale/en-us/dialog/notify_downloading_os.dialog
skill_update/locale/en-us/dialog/notify_downloading_update.dialog
skill_update/locale/en-us/dialog/notify_installation_complete.dialog
skill_update/locale/en-us/dialog/notify_installation_failed.dialog
skill_update/locale/en-us/dialog/notify_os_update_available.dialog
skill_update/neon_skill_update.egg-info/PKG-INFO
skill_update/neon_skill_update.egg-info/SOURCES.txt
skill_update/neon_skill_update.egg-info/dependency_links.txt
skill_update/neon_skill_update.egg-info/entry_points.txt
skill_update/neon_skill_update.egg-info/requires.txt
skill_update/neon_skill_update.egg-info/top_level.txt
neon_skill_update-3.1.2.dist-info/LICENSE.md
neon_skill_update-3.1.2.dist-info/METADATA
neon_skill_update-3.1.2.dist-info/WHEEL
neon_skill_update-3.1.2.dist-info/entry_points.txt
neon_skill_update-3.1.2.dist-info/top_level.txt
neon_skill_update-3.1.2.dist-info/RECORD
