Metadata-Version: 2.1
Name: neon-skill-update
Version: 3.1.2
Home-page: https://github.com/NeonGeckoCom/skill-update
Author: Neongecko
Author-email: developers@neon.ai
License: BSD-3-Clause
License-File: LICENSE.md
Requires-Dist: neon-utils~=1.12
Requires-Dist: ovos-utils>=0.0.35,~=0.0
Requires-Dist: ovos-workshop>=0.0.15,~=0.0
Provides-Extra: test
Requires-Dist: neon-minerva[padatious]~=0.3; extra == "test"
